{"nodes": [{"id": "conftest", "label": "conftest.py", "file_type": "code", "source_file": "tests/conftest.py", "source_location": "L1"}, {"id": "conftest_mock_gm_api", "label": "mock_gm_api()", "file_type": "code", "source_file": "tests/conftest.py", "source_location": "L25"}, {"id": "conftest_db_engine", "label": "db_engine()", "file_type": "code", "source_file": "tests/conftest.py", "source_location": "L70"}, {"id": "conftest_db_session", "label": "db_session()", "file_type": "code", "source_file": "tests/conftest.py", "source_location": "L96"}, {"id": "conftest_mock_config", "label": "mock_config()", "file_type": "code", "source_file": "tests/conftest.py", "source_location": "L116"}, {"id": "conftest_rationale_1", "label": "\u5168\u5c40\u6d4b\u8bd5\u5939\u5177 - PyTrading \u540e\u7aef\u6d4b\u8bd5\u57fa\u7840\u8bbe\u65bd\r \r \u63d0\u4f9b:\r - mock_gm_api: \u81ea\u52a8 mock \u6398\u91d1 SDK, \u9632\u6b62\u771f\u5b9e\u5bfc\u5165 (autou", "file_type": "rationale", "source_file": "tests/conftest.py", "source_location": "L1"}, {"id": "conftest_rationale_26", "label": "Mock \u6398\u91d1\u91cf\u5316 SDK, \u9632\u6b62\u6d4b\u8bd5\u4e2d\u771f\u5b9e\u5bfc\u5165 gm.api.\r \r     \u4f7f\u7528 types.ModuleType \u6784\u5efa\u6a21\u5757\u5bf9\u8c61, \u4f7f `from gm.a", "file_type": "rationale", "source_file": "tests/conftest.py", "source_location": "L26"}, {"id": "conftest_rationale_71", "label": "\u521b\u5efa SQLite \u5185\u5b58\u5f15\u64ce\u5e76\u521d\u59cb\u5316\u6240\u6709 ORM \u8868.\r \r     scope=session: \u6574\u4e2a\u6d4b\u8bd5\u4f1a\u8bdd\u5171\u4eab\u540c\u4e00\u5f15\u64ce, \u907f\u514d\u91cd\u590d\u5efa\u8868\u5f00\u9500.", "file_type": "rationale", "source_file": "tests/conftest.py", "source_location": "L71"}, {"id": "conftest_rationale_97", "label": "\u63d0\u4f9b\u81ea\u52a8\u56de\u6eda\u7684\u6570\u636e\u5e93\u4f1a\u8bdd.\r \r     \u6bcf\u4e2a\u6d4b\u8bd5\u51fd\u6570\u83b7\u5f97\u72ec\u7acb\u7684 session, \u6d4b\u8bd5\u7ed3\u675f\u540e\u81ea\u52a8 rollback + close,\r     \u4fdd\u8bc1\u6d4b\u8bd5\u4e4b\u95f4\u6570", "file_type": "rationale", "source_file": "tests/conftest.py", "source_location": "L97"}, {"id": "conftest_rationale_117", "label": "Config \u5de5\u5382 fixture, \u652f\u6301\u81ea\u5b9a\u4e49\u914d\u7f6e\u53c2\u6570.\r \r     \u7528\u6cd5:\r         def test_something(mock_config", "file_type": "rationale", "source_file": "tests/conftest.py", "source_location": "L117"}], "edges": [{"source": "conftest", "target": "sys", "relation": "imports", "confidence": "EXTRACTED", "source_file": "tests/conftest.py", "source_location": "L11", "weight": 1.0}, {"source": "conftest", "target": "types", "relation": "imports", "confidence": "EXTRACTED", "source_file": "tests/conftest.py", "source_location": "L12", "weight": 1.0}, {"source": "conftest", "target": "unittest_mock", "relation": "imports_from", "confidence": "EXTRACTED", "source_file": "tests/conftest.py", "source_location": "L13", "weight": 1.0}, {"source": "conftest", "target": "pytest", "relation": "imports", "confidence": "EXTRACTED", "source_file": "tests/conftest.py", "source_location": "L15", "weight": 1.0}, {"source": "conftest", "target": "sqlalchemy", "relation": "imports_from", "confidence": "EXTRACTED", "source_file": "tests/conftest.py", "source_location": "L16", "weight": 1.0}, {"source": "conftest", "target": "sqlalchemy_orm", "relation": "imports_from", "confidence": "EXTRACTED", "source_file": "tests/conftest.py", "source_location": "L17", "weight": 1.0}, {"source": "conftest", "target": "conftest_mock_gm_api", "relation": "contains", "confidence": "EXTRACTED", "source_file": "tests/conftest.py", "source_location": "L25", "weight": 1.0}, {"source": "conftest", "target": "conftest_db_engine", "relation": "contains", "confidence": "EXTRACTED", "source_file": "tests/conftest.py", "source_location": "L70", "weight": 1.0}, {"source": "conftest", "target": "conftest_db_session", "relation": "contains", "confidence": "EXTRACTED", "source_file": "tests/conftest.py", "source_location": "L96", "weight": 1.0}, {"source": "conftest", "target": "conftest_mock_config", "relation": "contains", "confidence": "EXTRACTED", "source_file": "tests/conftest.py", "source_location": "L116", "weight": 1.0}, {"source": "conftest_rationale_1", "target": "conftest", "relation": "rationale_for", "confidence": "EXTRACTED", "source_file": "tests/conftest.py", "source_location": "L1", "weight": 1.0}, {"source": "conftest_rationale_26", "target": "conftest_mock_gm_api", "relation": "rationale_for", "confidence": "EXTRACTED", "source_file": "tests/conftest.py", "source_location": "L26", "weight": 1.0}, {"source": "conftest_rationale_71", "target": "conftest_db_engine", "relation": "rationale_for", "confidence": "EXTRACTED", "source_file": "tests/conftest.py", "source_location": "L71", "weight": 1.0}, {"source": "conftest_rationale_97", "target": "conftest_db_session", "relation": "rationale_for", "confidence": "EXTRACTED", "source_file": "tests/conftest.py", "source_location": "L97", "weight": 1.0}, {"source": "conftest_rationale_117", "target": "conftest_mock_config", "relation": "rationale_for", "confidence": "EXTRACTED", "source_file": "tests/conftest.py", "source_location": "L117", "weight": 1.0}]}